MANIFEST.in
setup.py
netbox_maintenancecontract_plugin/__init__.py
netbox_maintenancecontract_plugin/filtersets.py
netbox_maintenancecontract_plugin/forms.py
netbox_maintenancecontract_plugin/models.py
netbox_maintenancecontract_plugin/navigation.py
netbox_maintenancecontract_plugin/tables.py
netbox_maintenancecontract_plugin/template_content.py
netbox_maintenancecontract_plugin/urls.py
netbox_maintenancecontract_plugin/views.py
netbox_maintenancecontract_plugin.egg-info/PKG-INFO
netbox_maintenancecontract_plugin.egg-info/SOURCES.txt
netbox_maintenancecontract_plugin.egg-info/dependency_links.txt
netbox_maintenancecontract_plugin.egg-info/not-zip-safe
netbox_maintenancecontract_plugin.egg-info/top_level.txt
netbox_maintenancecontract_plugin/api/serializers.py
netbox_maintenancecontract_plugin/api/urls.py
netbox_maintenancecontract_plugin/api/views.py
netbox_maintenancecontract_plugin/migrations/0001_initial.py
netbox_maintenancecontract_plugin/migrations/__init__.py
netbox_maintenancecontract_plugin/templates/netbox_maintenancecontract_plugin/contract.html
netbox_maintenancecontract_plugin/templates/netbox_maintenancecontract_plugin/contractdevice.html
netbox_maintenancecontract_plugin/templates/netbox_maintenancecontract_plugin/device.html
netbox_maintenancecontract_plugin/templates/netbox_maintenancecontract_plugin/supplier.html