Metadata-Version: 2.1
Name: netbox-maintenancecontract-plugin
Version: 0.2
Summary: Manage Maintenance Contracts Netbox
Download-URL: 
